tess_infos/__init__.py
tess_infos/tess_infos.py
tess_infos-0.1.1.dist-info/LICENSE.txt
tess_infos-0.1.1.dist-info/METADATA
tess_infos-0.1.1.dist-info/WHEEL
tess_infos-0.1.1.dist-info/top_level.txt
tess_infos-0.1.1.dist-info/RECORD
