Metadata-Version: 2.1
Name: tess-infos
Version: 0.1.1
Summary: Extremely fast Pythonic access to the full TICv8, GAIA DR2 and Banyan Sigma parameters for all TESS short-cadence targets
Home-page: https://github.com/MNGuenther/tess_infos
Author: Maximilian N. Günther & Adina D. Feinstein
Author-email: maxgue@mit.edu
License: MIT
Download-URL: https://github.com/MNGuenther/tess_infos
Platform: UNKNOWN
Classifier: Development Status :: 4 - Beta
Classifier: Intended Audience :: Science/Research
Classifier: License :: OSI Approved :: MIT License
Classifier: Programming Language :: Python
Requires-Dist: feather-format (>=0.4.1)
Requires-Dist: pyarrow
Requires-Dist: pandas
Requires-Dist: numpy
Requires-Dist: tqdm
Requires-Dist: matplotlib
